knoxdb/__init__.py
knoxdb/knox.py
knoxdb/setup.py
knoxdb-0.5.0.dist-info/LICENSE
knoxdb-0.5.0.dist-info/METADATA
knoxdb-0.5.0.dist-info/WHEEL
knoxdb-0.5.0.dist-info/top_level.txt
knoxdb-0.5.0.dist-info/RECORD
