Metadata-Version: 2.1
Name: knoxdb
Version: 0.5.0
Summary: Quickly create a PostgresSQL DB without the hassle.
Author-email: Knox Dobbins <knox.dobbins@gmail.com>
Classifier: Programming Language :: Python :: 3
Classifier: License :: OSI Approved :: MIT License
Classifier: Operating System :: OS Independent
Requires-Python: >=3.7
License-File: LICENSE
